{
  "name": "hefeng-mcp-weather",
  "description": "hefeng-mcp-weather MCP Server",
  "url": "hefeng-mcp-weather",
  "protocol_version": "MCP/1.0",
  "capabilities": [
    {
      "name": "get-weather",
      "type": "tool",
      "description": "获取中国国内的天气预报"
    }
  ],
  "installation": {
    "command": "npx",
    "args": [
      "-y",
      "hefeng-mcp-weather"
    ],
    "env": {}
  },
  "_id": "24818feb-2cb0-43f0-857f-5c6827227f5e",
  "_registeredAt": "2025-05-06T11:05:02.078Z",
  "_updatedAt": "2025-05-06T11:05:02.078Z",
  "_status": "unknown",
  "_lastChecked": null,
  "_kvId": "24818feb-2cb0-43f0-857f-5c6827227f5e"
}