{
  "name": "@marcusdb/github-mcp-server-ts",
  "description": "@marcusdb/github-mcp-server-ts MCP Server",
  "url": "@marcusdb/github-mcp-server-ts",
  "protocol_version": "MCP/1.0",
  "capabilities": [
    {
      "name": "create_or_update_file",
      "type": "tool",
      "description": "Create or update a single file in a GitHub repository"
    },
    {
      "name": "search_repositories",
      "type": "tool",
      "description": "Search for GitHub repositories"
    },
    {
      "name": "create_repository",
      "type": "tool",
      "description": "Create a new GitHub repository in your account"
    },
    {
      "name": "get_file_contents",
      "type": "tool",
      "description": "Get the contents of a file or directory from a GitHub repository"
    },
    {
      "name": "push_files",
      "type": "tool",
      "description": "Push multiple files to a GitHub repository in a single commit"
    },
    {
      "name": "create_issue",
      "type": "tool",
      "description": "Create a new issue in a GitHub repository"
    },
    {
      "name": "create_pull_request",
      "type": "tool",
      "description": "Create a new pull request in a GitHub repository"
    },
    {
      "name": "fork_repository",
      "type": "tool",
      "description": "Fork a GitHub repository to your account or specified organization"
    },
    {
      "name": "create_branch",
      "type": "tool",
      "description": "Create a new branch in a GitHub repository"
    },
    {
      "name": "list_commits",
      "type": "tool",
      "description": "Get list of commits of a branch in a GitHub repository"
    },
    {
      "name": "list_issues",
      "type": "tool",
      "description": "List issues in a GitHub repository with filtering options: milestone string (If an integer is passed, it should refer to a milestone by its number field. If the string * is passed, issues with any milestone are accepted. If the string none is passed, issues without milestones are returned.) ,state string(Indicates the state of the issues to return.Default: open - Can be one of: open, closed, all) ,assignee string  (Can be the name of a user. Pass in none for issues with no assigned user, and * for issues assigned to any user.) ,type string (Can be the name of an issue type. If the string * is passed, issues with any type are accepted. If the string none is passed, issues without type are returned.) ,creator string (The user that created the issue.) ,mentioned string (A user that's mentioned in the issue.) ,labels (An array of label names.)"
    },
    {
      "name": "update_issue",
      "type": "tool",
      "description": "Update an existing issue in a GitHub repository"
    },
    {
      "name": "add_issue_comment",
      "type": "tool",
      "description": "Add a comment to an existing issue"
    },
    {
      "name": "search_code",
      "type": "tool",
      "description": "Search for code across GitHub repositories"
    },
    {
      "name": "search_issues",
      "type": "tool",
      "description": "Search for issues and pull requests across GitHub repositories"
    },
    {
      "name": "search_users",
      "type": "tool",
      "description": "Search for users on GitHub"
    },
    {
      "name": "get_issue",
      "type": "tool",
      "description": "Get details of a specific issue in a GitHub repository."
    },
    {
      "name": "get_pull_request",
      "type": "tool",
      "description": "Get details of a specific pull request"
    },
    {
      "name": "list_pull_requests",
      "type": "tool",
      "description": "List and filter repository pull requests"
    },
    {
      "name": "create_pull_request_review",
      "type": "tool",
      "description": "Create a review on a pull request"
    },
    {
      "name": "merge_pull_request",
      "type": "tool",
      "description": "Merge a pull request"
    },
    {
      "name": "get_pull_request_files",
      "type": "tool",
      "description": "Get the list of files changed in a pull request"
    },
    {
      "name": "get_pull_request_status",
      "type": "tool",
      "description": "Get the combined status of all status checks for a pull request"
    },
    {
      "name": "update_pull_request_branch",
      "type": "tool",
      "description": "Update a pull request branch with the latest changes from the base branch"
    },
    {
      "name": "get_pull_request_comments",
      "type": "tool",
      "description": "Get the review comments on a pull request"
    },
    {
      "name": "get_pull_request_reviews",
      "type": "tool",
      "description": "Get the reviews on a pull request"
    },
    {
      "name": "list_sub_issues",
      "type": "tool",
      "description": "List sub issues of an issue"
    },
    {
      "name": "reprioritize_sub_issue",
      "type": "tool",
      "description": "Reprioritize a sub issue of an issue, make sure to specify either after_id or before_id, not both"
    },
    {
      "name": "remove_sub_issue",
      "type": "tool",
      "description": "Remove a sub issue of an issue, sub_issue_id is the id of the issue to be removed not the issue number"
    },
    {
      "name": "add_sub_issue",
      "type": "tool",
      "description": "Add a sub issue to an issue, sub_issue_id is the id of the issue to be added as sub-issue not the issue number"
    },
    {
      "name": "list_labels_for_issue",
      "type": "tool",
      "description": "List all labels for an issue"
    },
    {
      "name": "add_labels_to_issue",
      "type": "tool",
      "description": "Adds labels to an issue"
    },
    {
      "name": "set_labels_for_issue",
      "type": "tool",
      "description": "Sets the labels for an issue, replacing any existing labels"
    },
    {
      "name": "remove_label_from_issue",
      "type": "tool",
      "description": "Remove a label from an issue"
    },
    {
      "name": "remove_all_labels_from_issue",
      "type": "tool",
      "description": "Remove all labels from an issue"
    },
    {
      "name": "list_labels_for_repo",
      "type": "tool",
      "description": "List all labels for a repository"
    },
    {
      "name": "create_label",
      "type": "tool",
      "description": "Create a label for a repository"
    },
    {
      "name": "get_label",
      "type": "tool",
      "description": "Get a single label for a repository"
    },
    {
      "name": "update_label",
      "type": "tool",
      "description": "Update an existing label for a repository"
    },
    {
      "name": "delete_label",
      "type": "tool",
      "description": "Delete a label from a repository"
    },
    {
      "name": "list_labels_for_milestone",
      "type": "tool",
      "description": "List labels for issues in a milestone"
    },
    {
      "name": "list_milestones",
      "type": "tool",
      "description": "List milestones for a repository"
    },
    {
      "name": "create_milestone",
      "type": "tool",
      "description": "Create a milestone for a repository"
    },
    {
      "name": "get_milestone",
      "type": "tool",
      "description": "Get a single milestone for a repository"
    },
    {
      "name": "update_milestone",
      "type": "tool",
      "description": "Update an existing milestone for a repository"
    },
    {
      "name": "delete_milestone",
      "type": "tool",
      "description": "Delete a milestone from a repository"
    }
  ],
  "installation": {
    "command": "npx",
    "args": [
      "-y",
      "@marcusdb/github-mcp-server-ts"
    ],
    "env": {}
  },
  "_id": "55bcf603-33d6-4123-be44-f340e5d16b06",
  "_registeredAt": "2025-05-06T10:20:38.310Z",
  "_updatedAt": "2025-05-06T10:20:38.310Z",
  "_status": "unknown",
  "_lastChecked": null,
  "_kvId": "55bcf603-33d6-4123-be44-f340e5d16b06"
}