{
  "name": "Unknown",
  "description": "GitHub repository: chatmcp/mcp-directory",
  "url": "https://github.com/chatmcp/mcp-directory/",
  "protocol_version": "MCP/1.0",
  "capabilities": [
    {
      "name": "capabilities_unknown",
      "type": "tool",
      "description": "Server capabilities cannot be determined without authentication"
    }
  ],
  "tags": [
    "auto-discovered",
    "mcp-so",
    "unanalyzed",
    "github",
    "requires-installation"
  ],
  "installation": {
    "command": "git",
    "args": [
      "clone",
      "https://github.com/chatmcp/mcp-directory/"
    ]
  },
  "auth": {
    "type": "oauth",
    "instructions": "OAuth authentication required"
  },
  "_id": "623a33a5-3e4f-4ed6-b478-3437e4e51efc",
  "_registeredAt": "2025-06-20T15:44:31.184Z",
  "_updatedAt": "2025-06-20T15:44:31.184Z",
  "_status": "unknown",
  "_lastChecked": null,
  "_unverified": true,
  "_kvId": "623a33a5-3e4f-4ed6-b478-3437e4e51efc"
}