{
  "name": "@dealx/mcp-server",
  "description": "@dealx/mcp-server MCP Server",
  "url": "@dealx/mcp-server",
  "protocol_version": "MCP/1.0",
  "capabilities": [
    {
      "name": "search_ads",
      "type": "tool",
      "description": "Search for ads on the DealX platform"
    }
  ],
  "installation": {
    "command": "npx",
    "args": [
      "-y",
      "@dealx/mcp-server"
    ],
    "env": {}
  },
  "_id": "83388ed2-c530-4b8f-937e-e779567e3b11",
  "_registeredAt": "2025-05-06T10:21:37.673Z",
  "_updatedAt": "2025-05-06T10:21:37.673Z",
  "_status": "unknown",
  "_lastChecked": null,
  "_kvId": "83388ed2-c530-4b8f-937e-e779567e3b11"
}