{
  "name": "gorela-developer-mcp-server",
  "description": "gorela-developer-mcp-server MCP Server",
  "url": "gorela-developer-mcp-server",
  "protocol_version": "MCP/1.0",
  "capabilities": [
    {
      "name": "fetchGorelaApiDoc",
      "type": "tool",
      "description": "특정 URL 또는 경로에서 고릴라(Gorela) 연동 API 문서를 가져옵니다. 상대 경로나 전체 URL을 지정할 수 있습니다."
    }
  ],
  "installation": {
    "command": "npx",
    "args": [
      "-y",
      "gorela-developer-mcp-server"
    ],
    "env": {}
  },
  "_id": "d8bdf9ae-9fc1-4eed-8c19-4a660b2a533e",
  "_registeredAt": "2025-05-06T10:59:18.860Z",
  "_updatedAt": "2025-05-06T10:59:18.860Z",
  "_status": "unknown",
  "_lastChecked": null,
  "_kvId": "d8bdf9ae-9fc1-4eed-8c19-4a660b2a533e"
}