{
  "name": "mcp-repl",
  "description": "mcp-repl MCP Server",
  "url": "mcp-repl",
  "protocol_version": "MCP/1.0",
  "capabilities": [
    {
      "name": "executenodejs",
      "type": "tool",
      "description": "Execute JavaScript code directly with Node.js - supports ESM imports and all Node.js features"
    },
    {
      "name": "executedeno",
      "type": "tool",
      "description": "Execute JavaScript/TypeScript code with Deno - supports ESM imports and all Deno features"
    }
  ],
  "_id": "f5cc0184-bb66-4753-bbd0-2be2b32f6614",
  "_registeredAt": "2025-05-05T15:58:08.409Z",
  "_status": "unknown",
  "_lastChecked": null,
  "_kvId": "f5cc0184-bb66-4753-bbd0-2be2b32f6614"
}